{
    "type": "AnnotationPage",
    "@context": [
      "http://www.w3.org/ns/anno.jsonld"
    ],
    "items": [
      {
        "id": "e7a3b5b91fcb64a3",
        "type": "Annotation",
        "@context": [
          "http://www.w3.org/ns/anno.jsonld",
          "http://geojson.org/geojson-ld/geojson-context.jsonld",
          "http://iiif.io/api/presentation/3/context.json"
        ],
        "motivation": "georeferencing",
        "target": {
          "type": "Image",
          "source": "https://dlc.services/iiif-img/7/6/e8cc7a4b-706c-4dcb-bf5b-3aeae3a16b1c/full/full/0/default.jpg",
          "service": [
            {
              "@id": "https://dlc.services/iiif-img/7/6/e8cc7a4b-706c-4dcb-bf5b-3aeae3a16b1c",
              "type": "ImageService2"
            }
          ],
          "selector": {
            "type": "SvgSelector",
            "value": "<svg width=\"3115\" height=\"3843\"><polygon points=\"2507,2795 2592,1813 2613,1263 2626,1043 2623,888 2537,886 2545,583 2645,586 2648,499 1841,471 1004,487 1004,477 419,466 385,1294 375,2156 377,2966 1046,2917 1045,3446 1605,3428 1577,3119 1349,3128 1334,2883 1717,2856 1834,2837 2364,2793\" /></svg>"
          }
        },
        "body": {
          "type": "FeatureCollection",
          "transformation": {
            "type": "polynomial",
            "options": {
              "order": 1
            }
          },
          "features": [
            {
              "type": "Feature",
              "properties": {
                "pixelCoords": [
                  2193,
                  1844
                ]
              },
              "geometry": {
                "type": "Point",
                "coordinates": [
                  4.3575656,
                  52.0090916
                ]
              }
            },
            {
              "type": "Feature",
              "properties": {
                "pixelCoords": [
                  1825,
                  2795
                ]
              },
              "geometry": {
                "type": "Point",
                "coordinates": [
                  4.3576721,
                  52.008718
                ]
              }
            },
            {
              "type": "Feature",
              "properties": {
                "pixelCoords": [
                  2642,
                  587
                ]
              },
              "geometry": {
                "type": "Point",
                "coordinates": [
                  4.3574004,
                  52.0095952
                ]
              }
            },
            {
              "type": "Feature",
              "properties": {
                "pixelCoords": [
                  389,
                  2692
                ]
              },
              "geometry": {
                "type": "Point",
                "coordinates": [
                  4.3568884,
                  52.0084726
                ]
              }
            },
            {
              "type": "Feature",
              "properties": {
                "pixelCoords": [
                  430,
                  465
                ]
              },
              "geometry": {
                "type": "Point",
                "coordinates": [
                  4.356205,
                  52.0091649
                ]
              }
            },
            {
              "type": "Feature",
              "properties": {
                "pixelCoords": [
                  2617,
                  973
                ]
              },
              "geometry": {
                "type": "Point",
                "coordinates": [
                  4.3575328,
                  52.0094513
                ]
              }
            },
            {
              "type": "Feature",
              "properties": {
                "pixelCoords": [
                  1669,
                  2708
                ]
              },
              "geometry": {
                "type": "Point",
                "coordinates": [
                  4.3575556,
                  52.0087155
                ]
              }
            },
            {
              "type": "Feature",
              "properties": {
                "pixelCoords": [
                  2578,
                  1890
                ]
              },
              "geometry": {
                "type": "Point",
                "coordinates": [
                  4.3577812,
                  52.0091605
                ]
              }
            },
            {
              "type": "Feature",
              "properties": {
                "pixelCoords": [
                  1833,
                  477
                ]
              },
              "geometry": {
                "type": "Point",
                "coordinates": [
                  4.356933,
                  52.0094502
                ]
              }
            },
            {
              "type": "Feature",
              "properties": {
                "pixelCoords": [
                  2505,
                  2795
                ]
              },
              "geometry": {
                "type": "Point",
                "coordinates": [
                  4.3580243,
                  52.0088589
                ]
              }
            },
            {
              "type": "Feature",
              "properties": {
                "pixelCoords": [
                  1812,
                  895
                ]
              },
              "geometry": {
                "type": "Point",
                "coordinates": [
                  4.3570671,
                  52.0093198
                ]
              }
            },
            {
              "type": "Feature",
              "properties": {
                "pixelCoords": [
                  2644,
                  502
                ]
              },
              "geometry": {
                "type": "Point",
                "coordinates": [
                  4.3573761,
                  52.0096214
                ]
              }
            },
            {
              "type": "Feature",
              "properties": {
                "pixelCoords": [
                  1926,
                  892
                ]
              },
              "geometry": {
                "type": "Point",
                "coordinates": [
                  4.3571274,
                  52.0093433
                ]
              }
            },
            {
              "type": "Feature",
              "properties": {
                "pixelCoords": [
                  1659,
                  1915
                ]
              },
              "geometry": {
                "type": "Point",
                "coordinates": [
                  4.3573021,
                  52.0089633
                ]
              }
            },
            {
              "type": "Feature",
              "properties": {
                "pixelCoords": [
                  2540,
                  584
                ]
              },
              "geometry": {
                "type": "Point",
                "coordinates": [
                  4.3573475,
                  52.0095751
                ]
              }
            },
            {
              "type": "Feature",
              "properties": {
                "pixelCoords": [
                  1830,
                  567
                ]
              },
              "geometry": {
                "type": "Point",
                "coordinates": [
                  4.3569606,
                  52.0094245
                ]
              }
            },
            {
              "type": "Feature",
              "properties": {
                "pixelCoords": [
                  1943,
                  571
                ]
              },
              "geometry": {
                "type": "Point",
                "coordinates": [
                  4.3570178,
                  52.009448
                ]
              }
            },
            {
              "type": "Feature",
              "properties": {
                "pixelCoords": [
                  392,
                  1945
                ]
              },
              "geometry": {
                "type": "Point",
                "coordinates": [
                  4.3566535,
                  52.0087058
                ]
              }
            },
            {
              "type": "Feature",
              "properties": {
                "pixelCoords": [
                  2532,
                  888
                ]
              },
              "geometry": {
                "type": "Point",
                "coordinates": [
                  4.3574589,
                  52.0094626
                ]
              }
            },
            {
              "type": "Feature",
              "properties": {
                "pixelCoords": [
                  2617,
                  894
                ]
              },
              "geometry": {
                "type": "Point",
                "coordinates": [
                  4.3575046,
                  52.0094792
                ]
              }
            },
            {
              "type": "Feature",
              "properties": {
                "pixelCoords": [
                  1810,
                  973
                ]
              },
              "geometry": {
                "type": "Point",
                "coordinates": [
                  4.3571153,
                  52.0092782
                ]
              }
            }
          ]
        }
      }
    ]
  }